sncloud/__init__.py
sncloud/api.py
sncloud/cli.py
sncloud/endpoints.py
sncloud/exceptions.py
sncloud/models.py
sncloud-0.2.1.dist-info/METADATA
sncloud-0.2.1.dist-info/WHEEL
sncloud-0.2.1.dist-info/entry_points.txt
sncloud-0.2.1.dist-info/licenses/LICENSE
sncloud-0.2.1.dist-info/RECORD
