Metadata-Version: 2.4
Name: sncloud
Version: 0.2.1
Summary: Unofficial Python API client that allows you to access your Supernote files through the Supernote Cloud
Project-URL: Homepage, https://github.com/julianprester/sncloud
Project-URL: Changelog, https://github.com/julianprester/sncloud/releases
Project-URL: Issues, https://github.com/julianprester/sncloud/issues
Project-URL: CI, https://github.com/julianprester/sncloud/actions
Author-email: Julian Prester <hi@julianprester.com>
License: Apache-2.0
License-File: LICENSE
Requires-Python: >=3.10
Requires-Dist: click>=8.1.8
Requires-Dist: httpx>=0.28.1
Requires-Dist: pydantic>=2.10.5
